{
  "cookies": [
    {
      "name": "session-username",
      "value": "standard_user",
      "domain": "www.saucedemo.com",
      "path": "/",
      "expires": 1729540413,
      "httpOnly": false,
      "secure": false,
      "sameSite": "Lax"
    }
  ],
  "origins": [
    {
      "origin": "https://www.saucedemo.com",
      "localStorage": [
        {
          "name": "backtrace-guid",
          "value": "e516c1fe-f1d2-4b3a-9753-1666be8247fd"
        },
        {
          "name": "backtrace-last-active",
          "value": "1729539812548"
        }
      ]
    }
  ]
}